{
  "hasOpportunities": true,
  "updatedAt": "2026-04-11T12:34:53.789Z",
  "opportunities": [
    {
      "id": "h80ab774a",
      "sourceId": "ted-europa",
      "title": "Poland – Diffraction apparatus – Dostawa dyfraktometru rentgenowskiego z wyposażeniem dla IFJ PAN w Krakowie (DZP.260.11.2026)",
      "source": "TED Europa",
      "sourceTier": "internacional",
      "region": "EUROPA",
      "deadline": "2026-04-16T00:00:00.000Z",
      "amount": null,
      "currency": "",
      "amountUsd": null,
      "scoreTotal": 13,
      "recommendation": "No aplicar",
      "isViable": false,
      "url": "https://ted.europa.eu/en/notice/-/detail/170900-2026",
      "publicationNumber": "170900-2026"
    }
  ],
  "message": "Oportunidades detectadas por el agente UCI-F y evaluadas con matriz de elegibilidad. COLOMBIA: 0 | USA: 0 | EUROPA: 1"
}